{"flw.business.store.ArticleDynamics": {"article": {"abc_classification": "c",
            "articleNumber": 100103,
            "expressDelivery": 2,
            "expressDeliveryCost": 45,
            "fixCosts": 80,
            "minOrder": 30,
            "name": "Rueckleuchte",
            "normalDelivery": 3,
            "normalDeliveryCost": 20,
            "pricePerPallet": 180,
            "rebateAmount1": 75,
            "rebateAmount2": 140,
            "rebateCost1": 165,
            "rebateCost2": 150,
            "salePrice": 225
        },
        "palletsOfArticleInProcess": [{"flw.business.util.SerializableInteger":
                        [{"valueInt": 0},
                            {"valueInt": 0},
                            {"valueInt": 162},
                            {"valueInt": 0},
                            {"valueInt": 0}]}],
        "avgConsumption": 48,
        "consumption": 48,
        "estimatedRange": 3,
        "incomingPallets": 0,
        "lateDeliveredPallets": 0,
        "optimalOrderAmount": 0,
        "orderCosts": 0,
        "orderedPallets": 370,
        "salesIncome": 0
    }}