{
    "flw.business.statistics.ArticleAndOrderStatistics": {
        "roundNumber": 6,
        "process_pallet_count_overall": 607,
        "process_pallet_count_100101": 109,
        "process_pallet_count_100102": 220,
        "process_pallet_count_100103": 136,
        "process_pallet_count_100104": 142,
        "process_pallet_count_en": 0,
        "process_pallet_count_en_100101": 0,
        "process_pallet_count_en_100102": 0,
        "process_pallet_count_en_100103": 0,
        "process_pallet_count_en_100104": 0,
        "process_pallet_count_wv": 15,
        "process_pallet_count_wv_100101": 0,
        "process_pallet_count_wv_100102": 15,
        "process_pallet_count_wv_100103": 0,
        "process_pallet_count_wv_100104": 0,
        "process_pallet_count_la": 592,
        "process_pallet_count_la_100101": 109,
        "process_pallet_count_la_100102": 205,
        "process_pallet_count_la_100103": 136,
        "process_pallet_count_la_100104": 142,
        "process_pallet_count_wk": 0,
        "process_pallet_count_wk_100101": 0,
        "process_pallet_count_wk_100102": 0,
        "process_pallet_count_wk_100103": 0,
        "process_pallet_count_wk_100104": 0,
        "process_pallet_count_ve": 0,
        "process_pallet_count_ve_100101": 0,
        "process_pallet_count_ve_100102": 0,
        "process_pallet_count_ve_100103": 0,
        "process_pallet_count_ve_100104": 0,
        "ordered_pallet_count_overall": 480,
        "ordered_pallet_count_100101": 80,
        "ordered_pallet_count_100102": 250,
        "ordered_pallet_count_100103": 80,
        "ordered_pallet_count_100104": 70,
        "new_ordered_pallet_count_overall": 480,
        "new_ordered_pallet_count_100101": 80,
        "new_ordered_pallet_count_100102": 250,
        "new_ordered_pallet_count_100103": 80,
        "new_ordered_pallet_count_100104": 70,
        "ordered_but_not_delivered_overall": 0,
        "ordered_but_not_delivered_100101": 0,
        "ordered_but_not_delivered_100102": 0,
        "ordered_but_not_delivered_100103": 0,
        "ordered_but_not_delivered_100104": 0,
        "used_pallets_overall": 234,
        "used_pallets_100101": 26,
        "used_pallets_100102": 62,
        "used_pallets_100103": 42,
        "used_pallets_100104": 104,
        "job_pallet_count_overall": 234,
        "job_pallet_count_overall_100101": 26,
        "job_pallet_count_overall_100102": 62,
        "job_pallet_count_overall_100103": 42,
        "job_pallet_count_overall_100104": 104,
        "job_pallet_count_open_overall": 0,
        "job_pallet_count_open_100101": 0,
        "job_pallet_count_open_100102": 0,
        "job_pallet_count_open_100103": 0,
        "job_pallet_count_open_100104": 0,
        "job_pallet_count_new_overall": 234,
        "job_pallet_count_new_overall_100101": 26,
        "job_pallet_count_new_overall_100102": 62,
        "job_pallet_count_new_overall_100103": 42,
        "job_pallet_count_new_overall_100104": 104,
        "job_pallet_count_late_overall": 0,
        "job_pallet_count_late_100101": 0,
        "job_pallet_count_late_100102": 0,
        "job_pallet_count_late_100103": 0,
        "job_pallet_count_late_100104": 0,
        "variable_order_costs": 23904,
        "variable_order_costs_100101": 0,
        "variable_order_costs_100102": 23904,
        "variable_order_costs_100103": 0,
        "variable_order_costs_100104": 0,
        "fix_order_costs": 400



    }
}